MR22142UNO/__init__.py
MR22142UNO/metodos.py
mr22142uno-0.1.0.dist-info/METADATA
mr22142uno-0.1.0.dist-info/WHEEL
mr22142uno-0.1.0.dist-info/top_level.txt
mr22142uno-0.1.0.dist-info/RECORD
